RGB Mixer/src/pwm.v
`default_nettype none
`timescale 1ns/1ns
module pwm (
    input wire clk,
    input wire reset,
    output wire out,
    input wire [7:0] level
    );

    reg [7:0]count;

    /*Counter*/
    always @ (posedge clk)
    begin
        if (reset)
            begin
                count <= 8'b0;
            end

        else
            begin
                if (count == 8'hFF)
                    count <= 8'h00;
                else
                    count <= count + 1'b1;
            end
    end

    assign out = ((count < level) && (!reset == 1)) ? 1'b1 : 1'b0;

endmodule

RGB Mixer/src/encoder.v
`default_nettype none
`timescale 1ns/1ns
module encoder #(
    parameter WIDTH = 8,
    parameter JUMP_VALUE = 1)
    (
    input clk,
    input reset,
    input a,
    input b,
    output reg [WIDTH-1:0] value
);
    reg [3:0]code;

    /*value to store old and new A and B*/
    always @ (posedge clk)
    begin
        code <= {a, code[3], b, code[1]};
    end

    always @  (posedge clk)
    begin
        if (reset)
            value <= 0;
        else 
            begin
                casex(code)
                    4'b1000: begin
                        value <= value + JUMP_VALUE;
                    end
                    4'b0111: begin
                        value <= value + JUMP_VALUE;
                    end
                    4'b0010: begin
                        value <= value - JUMP_VALUE;
                    end
                    4'b1101: begin
                        value <= value - JUMP_VALUE;
                    end
                endcase
            end
    end

endmodule

RGB Mixer/src/debounce.v
`default_nettype none
`timescale 1ns/1ns
module debounce (
    input wire clk,
    input wire reset,
    input wire button,
    output reg debounced
);

reg [7:0]sreg;

always @ (posedge clk)
begin
    if (reset)
    begin
        sreg <= 8'b0;
        debounced <= 1'b0;
    end
    else
        begin
            sreg <= {sreg[6:0],button};
        end
    if (sreg == 8'hFF)
        debounced <= 1'b1;
    
    if (sreg == 8'h0)
        debounced <= 1'b0;
end

endmodule

RGB Mixer/src/rgb_mixer.v
`default_nettype none
`timescale 1ns/1ns
module rgb_mixer (
    input clk,
    input reset,
    input enc0_a,
    input enc0_b,
    input enc1_a,
    input enc1_b,
    input enc2_a,
    input enc2_b,
    output pwm0_out,
    output pwm1_out,
    output pwm2_out
);
    wire enc0_a_out, enc0_b_out;
    wire [7:0]enc0, enc1, enc2;
    wire enc1_a_out, enc1_b_out;
    wire enc2_a_out, enc2_b_out;

    /*enc0*/
    debounce d1 (clk, reset, enc0_a, enc0_a_out);
    debounce d2 (clk, reset, enc0_b, enc0_b_out);
    encoder e1 (clk, reset, enc0_a_out, enc0_b_out, enc0);
    pwm p1 (clk, reset, pwm0_out, enc0);

    /*enc1*/
    debounce d3 (clk, reset, enc1_a, enc1_a_out);
    debounce d4 (clk, reset, enc1_b, enc1_b_out);
    encoder e2 (clk, reset, enc1_a_out, enc1_b_out, enc1);
    pwm p2 (clk, reset, pwm1_out, enc1);

    /*enc2*/
    debounce d5 (clk, reset, enc2_a, enc2_a_out);
    debounce d6 (clk, reset, enc2_b, enc2_b_out);
    encoder e3 (clk, reset, enc2_a_out, enc2_b_out, enc2);
    pwm p3 (clk, reset, pwm2_out, enc2);

endmodule

RGB Mixer/rgb_mixer.vcd
$date
	Wed May 18 18:37:28 2022
$end
$version
	Icarus Verilog
$end
$timescale
	1ns
$end
$scope module rgb_mixer $end
$var wire 1 ! clk $end
$var wire 1 " enc0_a $end
$var wire 1 # enc0_b $end
$var wire 1 $ enc1_a $end
$var wire 1 % enc1_b $end
$var wire 1 & enc2_a $end
$var wire 1 ' enc2_b $end
$var wire 1 ( reset $end
$var wire 1 ) pwm2_out $end
$var wire 1 * pwm1_out $end
$var wire 1 + pwm0_out $end
$var wire 1 , enc2_b_out $end
$var wire 1 - enc2_a_out $end
$var wire 8 . enc2 [7:0] $end
$var wire 1 / enc1_b_out $end
$var wire 1 0 enc1_a_out $end
$var wire 8 1 enc1 [7:0] $end
$var wire 1 2 enc0_b_out $end
$var wire 1 3 enc0_a_out $end
$var wire 8 4 enc0 [7:0] $end
$scope module d1 $end
$var wire 1 " button $end
$var wire 1 ! clk $end
$var wire 1 ( reset $end
$var reg 1 3 debounced $end
$var reg 8 5 sreg [7:0] $end
$upscope $end
$scope module d2 $end
$var wire 1 # button $end
$var wire 1 ! clk $end
$var wire 1 ( reset $end
$var reg 1 2 debounced $end
$var reg 8 6 sreg [7:0] $end
$upscope $end
$scope module d3 $end
$var wire 1 $ button $end
$var wire 1 ! clk $end
$var wire 1 ( reset $end
$var reg 1 0 debounced $end
$var reg 8 7 sreg [7:0] $end
$upscope $end
$scope module d4 $end
$var wire 1 % button $end
$var wire 1 ! clk $end
$var wire 1 ( reset $end
$var reg 1 / debounced $end
$var reg 8 8 sreg [7:0] $end
$upscope $end
$scope module d5 $end
$var wire 1 & button $end
$var wire 1 ! clk $end
$var wire 1 ( reset $end
$var reg 1 - debounced $end
$var reg 8 9 sreg [7:0] $end
$upscope $end
$scope module d6 $end
$var wire 1 ' button $end
$var wire 1 ! clk $end
$var wire 1 ( reset $end
$var reg 1 , debounced $end
$var reg 8 : sreg [7:0] $end
$upscope $end
$scope module e1 $end
$var wire 1 3 a $end
$var wire 1 2 b $end
$var wire 1 ! clk $end
$var wire 1 ( reset $end
$var reg 4 ; code [3:0] $end
$var reg 8 < value [7:0] $end
$upscope $end
$scope module e2 $end
$var wire 1 0 a $end
$var wire 1 / b $end
$var wire 1 ! clk $end
$var wire 1 ( reset $end
$var reg 4 = code [3:0] $end
$var reg 8 > value [7:0] $end
$upscope $end
$scope module e3 $end
$var wire 1 - a $end
$var wire 1 , b $end
$var wire 1 ! clk $end
$var wire 1 ( reset $end
$var reg 4 ? code [3:0] $end
$var reg 8 @ value [7:0] $end
$upscope $end
$scope module p1 $end
$var wire 1 ! clk $end
$var wire 8 A level [7:0] $end
$var wire 1 ( reset $end
$var wire 1 + out $end
$var reg 8 B count [7:0] $end
$upscope $end
$scope module p2 $end
$var wire 1 ! clk $end
$var wire 8 C level [7:0] $end
$var wire 1 ( reset $end
$var wire 1 * out $end
$var reg 8 D count [7:0] $end
$upscope $end
$scope module p3 $end
$var wire 1 ! clk $end
$var wire 8 E level [7:0] $end
$var wire 1 ( reset $end
$var wire 1 ) out $end
$var reg 8 F count [7:0] $end
$upscope $end
$upscope $end
$enddefinitions $end
#0
$dumpvars
b0 F
b0 E
b0 D
b0 C
b0 B
b0 A
b0 @
bx ?
b0 >
bx =
b0 <
bx ;
b0 :
b0 9
b0 8
b0 7
b0 6
b0 5
b0 4
03
02
b0 1
00
0/
b0 .
0-
0,
0+
0*
0)
1(
0'
0&
0%
0$
0#
0"
1!
$end
#5000
0!
#10000
b0x0x ?
b0x0x =
b0x0x ;
1!
#15000
0!
#20000
b0 ;
b0 =
b0 ?
1!
#25000
0!
#30000
1!
#35000
0!
#40000
0(
1!
#45000
0!
#50000
b1 F
b1 D
b1 B
1!
#55000
0!
#60000
b10 B
b10 D
b10 F
1!
#65000
0!
#70000
b11 F
b11 D
b11 B
1!
#75000
0!
#80000
b100 B
b100 D
b100 F
1!
#85000
0!
#90000
b101 F
b101 D
b101 B
1!
#95000
0!
#100000
b110 B
b110 D
b110 F
1!
#105000
0!
#110000
1#
b111 F
b111 D
b111 B
1!
#115000
0!
#120000
0#
b1 6
b1000 B
b1000 D
b1000 F
1!
#125000
0!
#130000
b1001 F
b1001 D
b1001 B
b10 6
1!
#135000
0!
#140000
b100 6
b1010 B
b1010 D
b1010 F
1!
#145000
0!
#150000
b1011 F
b1011 D
b1011 B
b1000 6
1!
#155000
0!
#160000
b10000 6
b1100 B
b1100 D
b1100 F
1!
#165000
0!
#170000
b1101 F
b1101 D
b1101 B
b100000 6
1!
#175000
0!
#180000
b1000000 6
b1110 B
b1110 D
b1110 F
1!
#185000
0!
#190000
1"
b1111 F
b1111 D
b1111 B
b10000000 6
1!
#195000
0!
#200000
0"
b1 5
b0 6
b10000 B
b10000 D
b10000 F
1!
#205000
0!
#210000
1"
b10001 F
b10001 D
b10001 B
b10 5
1!
#215000
0!
#220000
b101 5
b10010 B
b10010 D
b10010 F
1!
#225000
0!
#230000
b10011 F
b10011 D
b10011 B
b1011 5
1!
#235000
0!
#240000
b10111 5
b10100 B
b10100 D
b10100 F
1!
#245000
0!
#250000
b10101 F
b10101 D
b10101 B
b101111 5
1!
#255000
0!
#260000
b1011111 5
b10110 B
b10110 D
b10110 F
1!
#265000
0!
#270000
b10111 F
b10111 D
b10111 B
b10111111 5
1!
#275000
0!
#280000
b1111111 5
b11000 B
b11000 D
b11000 F
1!
#285000
0!
#290000
b11001 F
b11001 D
b11001 B
b11111111 5
1!
#295000
0!
#300000
13
b11010 B
b11010 D
b11010 F
1!
#305000
0!
#310000
1#
b11011 F
b11011 D
b11011 B
b1000 ;
1!
#315000
0!
#320000
b1 6
b1100 ;
b1 4
b1 <
b1 A
b11100 B
b11100 D
b11100 F
1!
#325000
0!
#330000
b11101 F
b11101 D
b11101 B
b11 6
1!
#335000
0!
#340000
b111 6
b11110 B
b11110 D
b11110 F
1!
#345000
0!
#350000
b11111 F
b11111 D
b11111 B
b1111 6
1!
#355000
0!
#360000
b11111 6
b100000 B
b100000 D
b100000 F
1!
#365000
0!
#370000
b100001 F
b100001 D
b100001 B
b111111 6
1!
#375000
0!
#380000
b1111111 6
b100010 B
b100010 D
b100010 F
1!
#385000
0!
#390000
0"
b100011 F
b100011 D
b100011 B
b11111111 6
1!
#395000
0!
#400000
b11111110 5
12
b100100 B
b100100 D
b100100 F
1!
#405000
0!
#410000
b100101 F
b100101 D
b100101 B
b1110 ;
b11111100 5
1!
#415000
0!
#420000
b11111000 5
b1111 ;
b100110 B
b100110 D
b100110 F
1!
#425000
0!
#430000
b100111 F
b100111 D
b100111 B
b11110000 5
1!
#435000
0!
#440000
b11100000 5
b101000 B
b101000 D
b101000 F
1!
#445000
0!
#450000
b101001 F
b101001 D
b101001 B
b11000000 5
1!
#455000
0!
#460000
b10000000 5
b101010 B
b101010 D
b101010 F
1!
#465000
0!
#470000
b101011 F
b101011 D
b101011 B
b0 5
1!
#475000
0!
#480000
03
b101100 B
b101100 D
b101100 F
1!
#485000
0!
#490000
b101101 F
b101101 D
b101101 B
b111 ;
1!
#495000
0!
#500000
0#
b11 ;
b10 4
b10 <
b10 A
b101110 B
b101110 D
b101110 F
1!
#505000
0!
#510000
b101111 F
b101111 D
b101111 B
b11111110 6
1!
#515000
0!
#520000
b11111100 6
b110000 B
b110000 D
b110000 F
1!
#525000
0!
#530000
b110001 F
b110001 D
b110001 B
b11111000 6
1!
#535000
0!
#540000
b11110000 6
b110010 B
b110010 D
b110010 F
1!
#545000
0!
#550000
b110011 F
b110011 D
b110011 B
b11100000 6
1!
#555000
0!
#560000
b11000000 6
b110100 B
b110100 D
b110100 F
1!
#565000
0!
#570000
b110101 F
b110101 D
b110101 B
b10000000 6
1!
#575000
0!
#580000
b0 6
b110110 B
b110110 D
b110110 F
1!
#585000
0!
#590000
1"
b110111 F
b110111 D
b110111 B
02
1!
#595000
0!
#600000
0"
b1 5
b1 ;
b111000 B
b111000 D
b111000 F
1!
#605000
0!
#610000
b111001 F
b111001 D
b111001 B
b0 ;
b10 5
1!
#615000
0!
#620000
1"
b100 5
b111010 B
b111010 D
b111010 F
1!
#625000
0!
#630000
b111011 F
b111011 D
b111011 B
b1001 5
1!
#635000
0!
#640000
b10011 5
b111100 B
b111100 D
b111100 F
1!
#645000
0!
#650000
b111101 F
b111101 D
b111101 B
b100111 5
1!
#655000
0!
#660000
b1001111 5
b111110 B
b111110 D
b111110 F
1!
#665000
0!
#670000
b111111 F
b111111 D
b111111 B
b10011111 5
1!
#675000
0!
#680000
b111111 5
b1000000 B
b1000000 D
b1000000 F
1!
#685000
0!
#690000
1#
b1000001 F
b1000001 D
b1000001 B
b1111111 5
1!
#695000
0!
#700000
b11111111 5
b1 6
b1000010 B
b1000010 D
b1000010 F
1!
#705000
0!
#710000
b1000011 F
b1000011 D
b1000011 B
b11 6
13
1!
#715000
0!
#720000
b111 6
b1000 ;
b1000100 B
b1000100 D
b1000100 F
1!
#725000
0!
#730000
b1000101 F
b1000101 D
b1000101 B
b11 4
b11 <
b11 A
b1100 ;
b1111 6
1!
#735000
0!
#740000
b11111 6
b1000110 B
b1000110 D
b1000110 F
1!
#745000
0!
#750000
b1000111 F
b1000111 D
b1000111 B
b111111 6
1!
#755000
0!
#760000
b1111111 6
b1001000 B
b1001000 D
b1001000 F
1!
#765000
0!
#770000
b1001001 F
b1001001 D
b1001001 B
b11111111 6
1!
#775000
0!
#780000
12
b1001010 B
b1001010 D
b1001010 F
1!
#785000
0!
#790000
b1001011 F
b1001011 D
b1001011 B
b1110 ;
1!
#795000
0!
#800000
0"
b1111 ;
b1001100 B
b1001100 D
b1001100 F
1!
#805000
0!
#810000
b1001101 F
b1001101 D
b1001101 B
b11111110 5
1!
#815000
0!
#820000
b11111100 5
b1001110 B
b1001110 D
b1001110 F
1!
#825000
0!
#830000
b1001111 F
b1001111 D
b1001111 B
b11111000 5
1!
#835000
0!
#840000
b11110000 5
b1010000 B
b1010000 D
b1010000 F
1!
#845000
0!
#850000
b1010001 F
b1010001 D
b1010001 B
b11100000 5
1!
#855000
0!
#860000
b11000000 5
b1010010 B
b1010010 D
b1010010 F
1!
#865000
0!
#870000
b1010011 F
b1010011 D
b1010011 B
b10000000 5
1!
#875000
0!
#880000
b0 5
b1010100 B
b1010100 D
b1010100 F
1!
#885000
0!
#890000
b1010101 F
b1010101 D
b1010101 B
03
1!
#895000
0!
#900000
b111 ;
b1010110 B
b1010110 D
b1010110 F
1!
#905000
0!
#910000
0#
b1010111 F
b1010111 D
b1010111 B
b100 4
b100 <
b100 A
b11 ;
1!
#915000
0!
#920000
b11111110 6
b1011000 B
b1011000 D
b1011000 F
1!
#925000
0!
#930000
b1011001 F
b1011001 D
b1011001 B
b11111100 6
1!
#935000
0!
#940000
b11111000 6
b1011010 B
b1011010 D
b1011010 F
1!
#945000
0!
#950000
b1011011 F
b1011011 D
b1011011 B
b11110000 6
1!
#955000
0!
#960000
b11100000 6
b1011100 B
b1011100 D
b1011100 F
1!
#965000
0!
#970000
b1011101 F
b1011101 D
b1011101 B
b11000000 6
1!
#975000
0!
#980000
b10000000 6
b1011110 B
b1011110 D
b1011110 F
1!
#985000
0!
#990000
1"
b1011111 F
b1011111 D
b1011111 B
b0 6
1!
#995000
0!
#1000000
b1 5
02
b1100000 B
b1100000 D
b1100000 F
1!
#1005000
0!
#1010000
b1100001 F
b1100001 D
b1100001 B
b1 ;
b11 5
1!
#1015000
0!
#1020000
b111 5
b0 ;
b1100010 B
b1100010 D
b1100010 F
1!
#1025000
0!
#1030000
b1100011 F
b1100011 D
b1100011 B
b1111 5
1!
#1035000
0!
#1040000
b11111 5
b1100100 B
b1100100 D
b1100100 F
1!
#1045000
0!
#1050000
b1100101 F
b1100101 D
b1100101 B
b111111 5
1!
#1055000
0!
#1060000
b1111111 5
b1100110 B
b1100110 D
b1100110 F
1!
#1065000
0!
#1070000
b1100111 F
b1100111 D
b1100111 B
b11111111 5
1!
#1075000
0!
#1080000
13
b1101000 B
b1101000 D
b1101000 F
1!
#1085000
0!
#1090000
1#
b1101001 F
b1101001 D
b1101001 B
b1000 ;
1!
#1095000
0!
#1100000
b1 6
b1100 ;
b101 4
b101 <
b101 A
b1101010 B
b1101010 D
b1101010 F
1!
#1105000
0!
#1110000
b1101011 F
b1101011 D
b1101011 B
b11 6
1!
#1115000
0!
#1120000
b111 6
b1101100 B
b1101100 D
b1101100 F
1!
#1125000
0!
#1130000
b1101101 F
b1101101 D
b1101101 B
b1111 6
1!
#1135000
0!
#1140000
b11111 6
b1101110 B
b1101110 D
b1101110 F
1!
#1145000
0!
#1150000
b1101111 F
b1101111 D
b1101111 B
b111111 6
1!
#1155000
0!
#1160000
b1111111 6
b1110000 B
b1110000 D
b1110000 F
1!
#1165000
0!
#1170000
b1110001 F
b1110001 D
b1110001 B
b11111111 6
1!
#1175000
0!
#1180000
12
b1110010 B
b1110010 D
b1110010 F
1!
#1185000
0!
#1190000
b1110011 F
b1110011 D
b1110011 B
b1110 ;
1!
#1195000
0!
#1200000
0"
b1111 ;
b1110100 B
b1110100 D
b1110100 F
1!
#1205000
0!
#1210000
1"
b1110101 F
b1110101 D
b1110101 B
b11111110 5
1!
#1215000
0!
#1220000
0"
b11111101 5
b1110110 B
b1110110 D
b1110110 F
1!
#1225000
0!
#1230000
b1110111 F
b1110111 D
b1110111 B
b11111010 5
1!
#1235000
0!
#1240000
b11110100 5
b1111000 B
b1111000 D
b1111000 F
1!
#1245000
0!
#1250000
b1111001 F
b1111001 D
b1111001 B
b11101000 5
1!
#1255000
0!
#1260000
b11010000 5
b1111010 B
b1111010 D
b1111010 F
1!
#1265000
0!
#1270000
b1111011 F
b1111011 D
b1111011 B
b10100000 5
1!
#1275000
0!
#1280000
b1000000 5
b1111100 B
b1111100 D
b1111100 F
1!
#1285000
0!
#1290000
0#
b1111101 F
b1111101 D
b1111101 B
b10000000 5
1!
#1295000
0!
#1300000
1#
b0 5
b11111110 6
b1111110 B
b1111110 D
b1111110 F
1!
#1305000
0!
#1310000
0#
b1111111 F
b1111111 D
b1111111 B
b11111101 6
03
1!
#1315000
0!
#1320000
b11111010 6
b111 ;
b10000000 B
b10000000 D
b10000000 F
1!
#1325000
0!
#1330000
b10000001 F
b10000001 D
b10000001 B
b110 4
b110 <
b110 A
b11 ;
b11110100 6
1!
#1335000
0!
#1340000
b11101000 6
b10000010 B
b10000010 D
b10000010 F
1!
#1345000
0!
#1350000
b10000011 F
b10000011 D
b10000011 B
b11010000 6
1!
#1355000
0!
#1360000
b10100000 6
b10000100 B
b10000100 D
b10000100 F
1!
#1365000
0!
#1370000
b10000101 F
b10000101 D
b10000101 B
b1000000 6
1!
#1375000
0!
#1380000
b10000000 6
b10000110 B
b10000110 D
b10000110 F
1!
#1385000
0!
#1390000
b10000111 F
b10000111 D
b10000111 B
b0 6
1!
#1395000
0!
#1400000
1"
02
b10001000 B
b10001000 D
b10001000 F
1!
#1405000
0!
#1410000
0"
b10001001 F
b10001001 D
b10001001 B
b1 ;
b1 5
1!
#1415000
0!
#1420000
1"
b10 5
b0 ;
b10001010 B
b10001010 D
b10001010 F
1!
#1425000
0!
#1430000
b10001011 F
b10001011 D
b10001011 B
b101 5
1!
#1435000
0!
#1440000
b1011 5
b10001100 B
b10001100 D
b10001100 F
1!
#1445000
0!
#1450000
b10001101 F
b10001101 D
b10001101 B
b10111 5
1!
#1455000
0!
#1460000
b101111 5
b10001110 B
b10001110 D
b10001110 F
1!
#1465000
0!
#1470000
b10001111 F
b10001111 D
b10001111 B
b1011111 5
1!
#1475000
0!
#1480000
b10111111 5
b10010000 B
b10010000 D
b10010000 F
1!
#1485000
0!
#1490000
1#
b10010001 F
b10010001 D
b10010001 B
b1111111 5
1!
#1495000
0!
#1500000
b11111111 5
b1 6
b10010010 B
b10010010 D
b10010010 F
1!
#1505000
0!
#1510000
0#
b10010011 F
b10010011 D
b10010011 B
b11 6
13
1!
#1515000
0!
#1520000
1#
b110 6
b1000 ;
b10010100 B
b10010100 D
b10010100 F
1!
#1525000
0!
#1530000
b10010101 F
b10010101 D
b10010101 B
b111 4
b111 <
b111 A
b1100 ;
b1101 6
1!
#1535000
0!
#1540000
b11011 6
b10010110 B
b10010110 D
b10010110 F
1!
#1545000
0!
#1550000
b10010111 F
b10010111 D
b10010111 B
b110111 6
1!
#1555000
0!
#1560000
b1101111 6
b10011000 B
b10011000 D
b10011000 F
1!
#1565000
0!
#1570000
b10011001 F
b10011001 D
b10011001 B
b11011111 6
1!
#1575000
0!
#1580000
b10111111 6
b10011010 B
b10011010 D
b10011010 F
1!
#1585000
0!
#1590000
0"
b10011011 F
b10011011 D
b10011011 B
b1111111 6
1!
#1595000
0!
#1600000
1"
b11111110 5
b11111111 6
b10011100 B
b10011100 D
b10011100 F
1!
#1605000
0!
#1610000
0"
b10011101 F
b10011101 D
b10011101 B
12
b11111101 5
1!
#1615000
0!
#1620000
b11111010 5
b1110 ;
b10011110 B
b10011110 D
b10011110 F
1!
#1625000
0!
#1630000
b10011111 F
b10011111 D
b10011111 B
b1111 ;
b11110100 5
1!
#1635000
0!
#1640000
b11101000 5
b10100000 B
b10100000 D
b10100000 F
1!
#1645000
0!
#1650000
b10100001 F
b10100001 D
b10100001 B
b11010000 5
1!
#1655000
0!
#1660000
b10100000 5
b10100010 B
b10100010 D
b10100010 F
1!
#1665000
0!
#1670000
b10100011 F
b10100011 D
b10100011 B
b1000000 5
1!
#1675000
0!
#1680000
b10000000 5
b10100100 B
b10100100 D
b10100100 F
1!
#1685000
0!
#1690000
b10100101 F
b10100101 D
b10100101 B
b0 5
1!
#1695000
0!
#1700000
03
b10100110 B
b10100110 D
b10100110 F
1!
#1705000
0!
#1710000
b10100111 F
b10100111 D
b10100111 B
b111 ;
1!
#1715000
0!
#1720000
0#
b11 ;
b1000 4
b1000 <
b1000 A
b10101000 B
b10101000 D
b10101000 F
1!
#1725000
0!
#1730000
b10101001 F
b10101001 D
b10101001 B
b11111110 6
1!
#1735000
0!
#1740000
b11111100 6
b10101010 B
b10101010 D
b10101010 F
1!
#1745000
0!
#1750000
b10101011 F
b10101011 D
b10101011 B
b11111000 6
1!
#1755000
0!
#1760000
b11110000 6
b10101100 B
b10101100 D
b10101100 F
1!
#1765000
0!
#1770000
b10101101 F
b10101101 D
b10101101 B
b11100000 6
1!
#1775000
0!
#1780000
b11000000 6
b10101110 B
b10101110 D
b10101110 F
1!
#1785000
0!
#1790000
1"
b10101111 F
b10101111 D
b10101111 B
b10000000 6
1!
#1795000
0!
#1800000
b1 5
b0 6
b10110000 B
b10110000 D
b10110000 F
1!
#1805000
0!
#1810000
b10110001 F
b10110001 D
b10110001 B
02
b11 5
1!
#1815000
0!
#1820000
b111 5
b1 ;
b10110010 B
b10110010 D
b10110010 F
1!
#1825000
0!
#1830000
b10110011 F
b10110011 D
b10110011 B
b0 ;
b1111 5
1!
#1835000
0!
#1840000
b11111 5
b10110100 B
b10110100 D
b10110100 F
1!
#1845000
0!
#1850000
b10110101 F
b10110101 D
b10110101 B
b111111 5
1!
#1855000
0!
#1860000
b1111111 5
b10110110 B
b10110110 D
b10110110 F
1!
#1865000
0!
#1870000
b10110111 F
b10110111 D
b10110111 B
b11111111 5
1!
#1875000
0!
#1880000
13
b10111000 B
b10111000 D
b10111000 F
1!
#1885000
0!
#1890000
1#
b10111001 F
b10111001 D
b10111001 B
b1000 ;
1!
#1895000
0!
#1900000
0#
b1 6
b1100 ;
b1001 4
b1001 <
b1001 A
b10111010 B
b10111010 D
b10111010 F
1!
#1905000
0!
#1910000
1#
b10111011 F
b10111011 D
b10111011 B
b10 6
1!
#1915000
0!
#1920000
b101 6
b10111100 B
b10111100 D
b10111100 F
1!
#1925000
0!
#1930000
b10111101 F
b10111101 D
b10111101 B
b1011 6
1!
#1935000
0!
#1940000
b10111 6
b10111110 B
b10111110 D
b10111110 F
1!
#1945000
0!
#1950000
b10111111 F
b10111111 D
b10111111 B
b101111 6
1!
#1955000
0!
#1960000
b1011111 6
b11000000 B
b11000000 D
b11000000 F
1!
#1965000
0!
#1970000
b11000001 F
b11000001 D
b11000001 B
b10111111 6
1!
#1975000
0!
#1980000
b1111111 6
b11000010 B
b11000010 D
b11000010 F
1!
#1985000
0!
#1990000
0"
b11000011 F
b11000011 D
b11000011 B
b11111111 6
1!
#1995000
0!
#2000000
1"
b11111110 5
12
b11000100 B
b11000100 D
b11000100 F
1!
#2005000
0!
#2010000
b11000101 F
b11000101 D
b11000101 B
b1110 ;
b11111101 5
1!
#2015000
0!
#2020000
0"
b11111011 5
b1111 ;
b11000110 B
b11000110 D
b11000110 F
1!
#2025000
0!
#2030000
b11000111 F
b11000111 D
b11000111 B
b11110110 5
1!
#2035000
0!
#2040000
b11101100 5
b11001000 B
b11001000 D
b11001000 F
1!
#2045000
0!
#2050000
b11001001 F
b11001001 D
b11001001 B
b11011000 5
1!
#2055000
0!
#2060000
b10110000 5
b11001010 B
b11001010 D
b11001010 F
1!
#2065000
0!
#2070000
b11001011 F
b11001011 D
b11001011 B
b1100000 5
1!
#2075000
0!
#2080000
b11000000 5
b11001100 B
b11001100 D
b11001100 F
1!
#2085000
0!
#2090000
0#
b11001101 F
b11001101 D
b11001101 B
b10000000 5
1!
#2095000
0!
#2100000
b0 5
b11111110 6
b11001110 B
b11001110 D
b11001110 F
1!
#2105000
0!
#2110000
1#
b11001111 F
b11001111 D
b11001111 B
b11111100 6
03
1!
#2115000
0!
#2120000
0#
b11111001 6
b111 ;
b11010000 B
b11010000 D
b11010000 F
1!
#2125000
0!
#2130000
b11010001 F
b11010001 D
b11010001 B
b1010 4
b1010 <
b1010 A
b11 ;
b11110010 6
1!
#2135000
0!
#2140000
b11100100 6
b11010010 B
b11010010 D
b11010010 F
1!
#2145000
0!
#2150000
b11010011 F
b11010011 D
b11010011 B
b11001000 6
1!
#2155000
0!
#2160000
b10010000 6
b11010100 B
b11010100 D
b11010100 F
1!
#2165000
0!
#2170000
b11010101 F
b11010101 D
b11010101 B
b100000 6
1!
#2175000
0!
#2180000
b1000000 6
b11010110 B
b11010110 D
b11010110 F
1!
#2185000
0!
#2190000
1"
b11010111 F
b11010111 D
b11010111 B
b10000000 6
1!
#2195000
0!
#2200000
0"
b1 5
b0 6
b11011000 B
b11011000 D
b11011000 F
1!
#2205000
0!
#2210000
1"
b11011001 F
b11011001 D
b11011001 B
02
b10 5
1!
#2215000
0!
#2220000
b101 5
b1 ;
b11011010 B
b11011010 D
b11011010 F
1!
#2225000
0!
#2230000
b11011011 F
b11011011 D
b11011011 B
b0 ;
b1011 5
1!
#2235000
0!
#2240000
b10111 5
b11011100 B
b11011100 D
b11011100 F
1!
#2245000
0!
#2250000
b11011101 F
b11011101 D
b11011101 B
b101111 5
1!
#2255000
0!
#2260000
b1011111 5
b11011110 B
b11011110 D
b11011110 F
1!
#2265000
0!
#2270000
b11011111 F
b11011111 D
b11011111 B
b10111111 5
1!
#2275000
0!
#2280000
b1111111 5
b11100000 B
b11100000 D
b11100000 F
1!
#2285000
0!
#2290000
b11100001 F
b11100001 D
b11100001 B
b11111111 5
1!
#2295000
0!
#2300000
1#
13
b11100010 B
b11100010 D
b11100010 F
1!
#2305000
0!
#2310000
b11100011 F
b11100011 D
b11100011 B
b1000 ;
b1 6
1!
#2315000
0!
#2320000
b11 6
b1100 ;
b1011 4
b1011 <
b1011 A
b11100100 B
b11100100 D
b11100100 F
1!
#2325000
0!
#2330000
b11100101 F
b11100101 D
b11100101 B
b111 6
1!
#2335000
0!
#2340000
b1111 6
b11100110 B
b11100110 D
b11100110 F
1!
#2345000
0!
#2350000
b11100111 F
b11100111 D
b11100111 B
b11111 6
1!
#2355000
0!
#2360000
b111111 6
b11101000 B
b11101000 D
b11101000 F
1!
#2365000
0!
#2370000
b11101001 F
b11101001 D
b11101001 B
b1111111 6
1!
#2375000
0!
#2380000
b11111111 6
b11101010 B
b11101010 D
b11101010 F
1!
#2385000
0!
#2390000
0"
b11101011 F
b11101011 D
b11101011 B
12
1!
#2395000
0!
#2400000
b11111110 5
b1110 ;
b11101100 B
b11101100 D
b11101100 F
1!
#2405000
0!
#2410000
b11101101 F
b11101101 D
b11101101 B
b1111 ;
b11111100 5
1!
#2415000
0!
#2420000
b11111000 5
b11101110 B
b11101110 D
b11101110 F
1!
#2425000
0!
#2430000
b11101111 F
b11101111 D
b11101111 B
b11110000 5
1!
#2435000
0!
#2440000
b11100000 5
b11110000 B
b11110000 D
b11110000 F
1!
#2445000
0!
#2450000
b11110001 F
b11110001 D
b11110001 B
b11000000 5
1!
#2455000
0!
#2460000
b10000000 5
b11110010 B
b11110010 D
b11110010 F
1!
#2465000
0!
#2470000
b11110011 F
b11110011 D
b11110011 B
b0 5
1!
#2475000
0!
#2480000
03
b11110100 B
b11110100 D
b11110100 F
1!
#2485000
0!
#2490000
0#
b11110101 F
b11110101 D
b11110101 B
b111 ;
1!
#2495000
0!
#2500000
b11111110 6
b11 ;
b1100 4
b1100 <
b1100 A
b11110110 B
b11110110 D
b11110110 F
1!
#2505000
0!
#2510000
b11110111 F
b11110111 D
b11110111 B
b11111100 6
1!
#2515000
0!
#2520000
b11111000 6
b11111000 B
b11111000 D
b11111000 F
1!
#2525000
0!
#2530000
b11111001 F
b11111001 D
b11111001 B
b11110000 6
1!
#2535000
0!
#2540000
b11100000 6
b11111010 B
b11111010 D
b11111010 F
1!
#2545000
0!
#2550000
b11111011 F
b11111011 D
b11111011 B
b11000000 6
1!
#2555000
0!
#2560000
b10000000 6
b11111100 B
b11111100 D
b11111100 F
1!
#2565000
0!
#2570000
b11111101 F
b11111101 D
b11111101 B
b0 6
1!
#2575000
0!
#2580000
02
b11111110 B
b11111110 D
b11111110 F
1!
#2585000
0!
#2590000
1"
b11111111 F
b11111111 D
b11111111 B
b1 ;
1!
#2595000
0!
#2600000
1+
b1 5
b0 ;
b0 B
b0 D
b0 F
1!
#2605000
0!
#2610000
b1 F
b1 D
b1 B
b11 5
1!
#2615000
0!
#2620000
b111 5
b10 B
b10 D
b10 F
1!
#2625000
0!
#2630000
b11 F
b11 D
b11 B
b1111 5
1!
#2635000
0!
#2640000
b11111 5
b100 B
b100 D
b100 F
1!
#2645000
0!
#2650000
b101 F
b101 D
b101 B
b111111 5
1!
#2655000
0!
#2660000
b1111111 5
b110 B
b110 D
b110 F
1!
#2665000
0!
#2670000
b111 F
b111 D
b111 B
b11111111 5
1!
#2675000
0!
#2680000
13
b1000 B
b1000 D
b1000 F
1!
#2685000
0!
#2690000
1#
b1001 F
b1001 D
b1001 B
b1000 ;
1!
#2695000
0!
#2700000
b1 6
b1100 ;
b1101 4
b1101 <
b1101 A
b1010 B
b1010 D
b1010 F
1!
#2705000
0!
#2710000
b1011 F
b1011 D
b1011 B
b11 6
1!
#2715000
0!
